eazyml_model/__init__.cp310-win_amd64.pyd
eazyml_model/__init__.cp311-win_amd64.pyd
eazyml_model/__init__.cp312-win_amd64.pyd
eazyml_model/__init__.cp37-win_amd64.pyd
eazyml_model/__init__.cp38-win_amd64.pyd
eazyml_model/__init__.cp39-win_amd64.pyd
eazyml_model/__init__.cpython-310-x86_64-linux-gnu.so
eazyml_model/__init__.cpython-311-x86_64-linux-gnu.so
eazyml_model/__init__.cpython-312-x86_64-linux-gnu.so
eazyml_model/__init__.cpython-37m-x86_64-linux-gnu.so
eazyml_model/__init__.cpython-38-x86_64-linux-gnu.so
eazyml_model/__init__.cpython-39-x86_64-linux-gnu.so
eazyml_model/eazyml.cp310-win_amd64.pyd
eazyml_model/eazyml.cp311-win_amd64.pyd
eazyml_model/eazyml.cp312-win_amd64.pyd
eazyml_model/eazyml.cp37-win_amd64.pyd
eazyml_model/eazyml.cp38-win_amd64.pyd
eazyml_model/eazyml.cp39-win_amd64.pyd
eazyml_model/eazyml.cpython-310-x86_64-linux-gnu.so
eazyml_model/eazyml.cpython-311-x86_64-linux-gnu.so
eazyml_model/eazyml.cpython-312-x86_64-linux-gnu.so
eazyml_model/eazyml.cpython-37m-x86_64-linux-gnu.so
eazyml_model/eazyml.cpython-38-x86_64-linux-gnu.so
eazyml_model/eazyml.cpython-39-x86_64-linux-gnu.so
eazyml_model/src/__init__.cp310-win_amd64.pyd
eazyml_model/src/__init__.cp311-win_amd64.pyd
eazyml_model/src/__init__.cp312-win_amd64.pyd
eazyml_model/src/__init__.cp37-win_amd64.pyd
eazyml_model/src/__init__.cp38-win_amd64.pyd
eazyml_model/src/__init__.cp39-win_amd64.pyd
eazyml_model/src/__init__.cpython-310-x86_64-linux-gnu.so
eazyml_model/src/__init__.cpython-311-x86_64-linux-gnu.so
eazyml_model/src/__init__.cpython-312-x86_64-linux-gnu.so
eazyml_model/src/__init__.cpython-37m-x86_64-linux-gnu.so
eazyml_model/src/__init__.cpython-38-x86_64-linux-gnu.so
eazyml_model/src/__init__.cpython-39-x86_64-linux-gnu.so
eazyml_model/src/build_model/__init__.cp310-win_amd64.pyd
eazyml_model/src/build_model/__init__.cp311-win_amd64.pyd
eazyml_model/src/build_model/__init__.cp312-win_amd64.pyd
eazyml_model/src/build_model/__init__.cp37-win_amd64.pyd
eazyml_model-0.0.4.dist-info/METADATA
eazyml_model-0.0.4.dist-info/WHEEL
eazyml_model-0.0.4.dist-info/top_level.txt
eazyml_model-0.0.4.dist-info/RECORD
